LICENSE
MANIFEST.in
NOTICE.md
README.md
setup.py
cfneval/__init__.py
cfneval/behave_cfn.py
cfneval/behave_steps.py
cfneval/cli.py
cfneval/resource_attribute_generator.py
cfneval/resource_attributes.py
cfneval/template_evaluator.py
cfneval.egg-info/PKG-INFO
cfneval.egg-info/SOURCES.txt
cfneval.egg-info/dependency_links.txt
cfneval.egg-info/entry_points.txt
cfneval.egg-info/requires.txt
cfneval.egg-info/top_level.txt
cfneval/resource_attribute_bundle/__init__.py
cfneval/resource_attribute_bundle/acm.py
cfneval/resource_attribute_bundle/ecs.py
cfneval/resource_attribute_bundle/elbv2.py
cfneval/resource_attribute_bundle/ssm.py
cfneval/steps/__init__.py
cfneval/steps/behave_given.py
cfneval/steps/behave_then.py
cfneval/steps/behave_when.py