Metadata-Version: 2.2
Name: cfneval
Version: 1.1.0
Summary: Evaluate and unit test CloudFormation templates
Home-page: https://github.com/vanguard-oss/cfneval
Author: Vanguard
Author-email: opensource@vanguard.com
License: Apache License 2.0
Classifier: Development Status :: 5 - Production/Stable
Classifier: Intended Audience :: Developers
Classifier: Natural Language :: English
Classifier: License :: OSI Approved :: Apache Software License
Classifier: Programming Language :: Python :: 3
Classifier: Programming Language :: Python :: 3.9
Classifier: Programming Language :: Python :: 3.10
Classifier: Programming Language :: Python :: 3.11
License-File: LICENSE
License-File: NOTICE.md
Requires-Dist: behave>=1.0.25
Requires-Dist: jsonpath_ng<2.0.0
Requires-Dist: PyYAML>=5.4.1
Requires-Dist: click
Requires-Dist: cfn-flip
Requires-Dist: python-benedict
Dynamic: author
Dynamic: author-email
Dynamic: classifier
Dynamic: description
Dynamic: description-content-type
Dynamic: home-page
Dynamic: license
Dynamic: requires-dist
Dynamic: summary
